mecoda_orange/__init__.py
mecoda_orange/aire_ciudadano.py
mecoda_orange/canAIRio_fixed.py
mecoda_orange/canAIRio_fixed_extra_info.py
mecoda_orange/canAIRio_mobile.py
mecoda_orange/canAIRio_mobile_extra_info.py
mecoda_orange/inaturalist.py
mecoda_orange/minka.py
mecoda_orange/minka_get_images.py
mecoda_orange/minka_marine_filter.py
mecoda_orange/minka_mentions.py
mecoda_orange/smartcitizen_data.py
mecoda_orange/smartcitizen_search.py
mecoda_orange/icons/anchor-minka.png
mecoda_orange/icons/arrow-down-wide-short-solid-minka.png
mecoda_orange/icons/camera-minka.png
mecoda_orange/icons/camera-verde.png
mecoda_orange/icons/canairio_fixed_last_hour.png
mecoda_orange/icons/canairio_fixed_widget.png
mecoda_orange/icons/canairio_logo_gris.png
mecoda_orange/icons/canairio_logo_rosa.png
mecoda_orange/icons/canairio_mobile_total.png
mecoda_orange/icons/canairio_mobile_track.png
mecoda_orange/icons/canairio_mobile_widget.png
mecoda_orange/icons/canairio_workflow.png
mecoda_orange/icons/circle-info-solid-gris-oscuro.png
mecoda_orange/icons/circle-info-solid-gris.png
mecoda_orange/icons/circle-info-solid-minka.png
mecoda_orange/icons/circle-info-solid-rosa.png
mecoda_orange/icons/circle-info-solid-verde.png
mecoda_orange/icons/cos4cloud.png
mecoda_orange/icons/cos4cloud_color.png
mecoda_orange/icons/cos4cloud_v2.png
mecoda_orange/icons/filtrar.png
mecoda_orange/icons/fish-minka.png
mecoda_orange/icons/globe-minka.png
mecoda_orange/icons/ictio-circular.png
mecoda_orange/icons/ictio.png
mecoda_orange/icons/ictio_widget.png
mecoda_orange/icons/inat-logo.png
mecoda_orange/icons/inaturalist_filter.png
mecoda_orange/icons/kduino.png
mecoda_orange/icons/leaf-solid-minka.png
mecoda_orange/icons/logo-aire-ciudadano.png
mecoda_orange/icons/logo-cos4cloud-middle.png
mecoda_orange/icons/map_filter_workflow.png
mecoda_orange/icons/map_filter_workflow2.png
mecoda_orange/icons/marine_filter_widget.png
mecoda_orange/icons/mecoda_share.png
mecoda_orange/icons/minka-logo.png
mecoda_orange-2.6.7.dist-info/METADATA
mecoda_orange-2.6.7.dist-info/WHEEL
mecoda_orange-2.6.7.dist-info/entry_points.txt
mecoda_orange-2.6.7.dist-info/top_level.txt
mecoda_orange-2.6.7.dist-info/RECORD
