Metadata-Version: 2.1
Name: mecoda_orange
Version: 2.6.7
Summary: Orange Data Minining Add-on containing MECODA widgets to analyse data from citizen science observatories
Home-page: https://github.com/eosc-cos4cloud/mecoda-orange
Author: Ana Alvarez, ICM-CSIC
Author-email: ana.alvarez@icm.csic.es
License: BSD
Keywords: orange3 add-on,orange,data mining
Classifier: License :: OSI Approved :: European Union Public Licence 1.2 (EUPL 1.2)
Classifier: Environment :: X11 Applications :: Qt
Classifier: Environment :: Console
Classifier: Environment :: Plugins
Classifier: Programming Language :: Python :: 3
Classifier: Programming Language :: Python :: 3.7
Classifier: Development Status :: 4 - Beta
Classifier: Topic :: Scientific/Engineering :: Visualization
Classifier: Topic :: Software Development :: Libraries :: Python Modules
Classifier: Operating System :: OS Independent
Classifier: Intended Audience :: Education
Classifier: Intended Audience :: Science/Research
Classifier: Intended Audience :: Developers
Requires-Dist: pandas >=1.4.4
Requires-Dist: Orange3 >=3.31.1
Requires-Dist: pyodcollect >=1.1.0
Requires-Dist: mecoda-minka >=1.9.5
Requires-Dist: mecoda-inat >=1.0.2
Requires-Dist: smartcitizen-connector >=1.2.0
Requires-Dist: nest-asyncio
Requires-Dist: pydantic >=2.4.2
Requires-Dist: tabulate
Requires-Dist: timezonefinder <5.0.0
